bresh/__init__.py
bresh/cli.py
bresh/config.py
bresh/errors.py
bresh/apis/__init__.py
bresh/apis/cs_portal_api.py
bresh/apis/pypi_client.py
bresh/apis/pypi_smb.py
bresh/apis/rest_api.py
bresh/apis/package/__init__.py
bresh/apis/package/helpers.py
bresh/apis/package/models.py
bresh/apis/package/package_api.py
bresh/handlers/__init__.py
bresh/handlers/app_template.py
bresh/handlers/base_handler.py
bresh/handlers/base_resource.py
bresh/handlers/blueprint.py
bresh/handlers/cs.py
bresh/handlers/deployed_app.py
bresh/handlers/offline_pypi.py
bresh/handlers/package.py
bresh/handlers/resource.py
bresh/handlers/sandbox.py
bresh/handlers/shell.py
bresh/handlers/shellfoundry.py
bresh/handlers/smb_client.py
bresh/handlers/snmp_simulator_client.py
bresh/utils/__init__.py
bresh/utils/cli_utils.py
bresh/utils/complete.py
bresh/utils/config_utils.py
bresh/utils/dict_utils.py
bresh/utils/download_file.py
bresh/utils/not_set.py
bresh/utils/progress_bar.py
bresh-0.19.1.dist-info/METADATA
bresh-0.19.1.dist-info/WHEEL
bresh-0.19.1.dist-info/entry_points.txt
bresh-0.19.1.dist-info/top_level.txt
bresh-0.19.1.dist-info/RECORD
