Metadata-Version: 2.1
Name: bresh
Version: 0.19.1
Requires-Python: ~=3.11
Requires-Dist: attrs ~=23.0
Requires-Dist: cloudshell-automation-api <2024,>=2022
Requires-Dist: cloudshell-rest-api ~=9.0
Requires-Dist: pysmb ~=1.2
Requires-Dist: dynaconf ~=3.1
Requires-Dist: pydantic ~=2.4
Requires-Dist: click ~=8.1
Requires-Dist: diskcache ~=5.4
Requires-Dist: requests-toolbelt ~=1.0
Requires-Dist: alive-progress ~=3.1
Requires-Dist: cryptography ~=40.0
Requires-Dist: pyyaml ~=6.0
Requires-Dist: build ~=0.10
Requires-Dist: rich ~=13.0
Requires-Dist: cached-property ~=1.5
Requires-Dist: keyring ~=24.0
Requires-Dist: xmltodict ~=0.13
Requires-Dist: humanize ~=4.8
